README.rst
setup.cfg
setup.py
tinypath.py
tinypath.egg-info/PKG-INFO
tinypath.egg-info/SOURCES.txt
tinypath.egg-info/dependency_links.txt
tinypath.egg-info/top_level.txt