Metadata-Version: 1.1
Name: tinypath
Version: 0.1.1
Summary: Tinypath is a tiny object-oriented file path module that provides only the most crucial and commonly needed functionality, making it easy to learn and efficient to use.
Home-page: http://github.com/karimbahgat/tinypath
Author: Karim Bahgat
Author-email: karim.bahgat.norway@gmail.com
License: MIT
Keywords: paths files folders organizing
Platform: UNKNOWN
Classifier: License :: OSI Approved
Classifier: Programming Language :: Python
Classifier: Development Status :: 4 - Beta
Classifier: Intended Audience :: Developers
Classifier: Intended Audience :: Science/Research
Classifier: Intended Audience :: End Users/Desktop
